Metadata-Version: 2.1
Name: bonniebully
Version: 1.0.3
Summary: This package was developed to simplify date manipulation.
Home-page: https://github.com/delvidioneto/bonniebully
Author: Delvidio Demarchi Neto
Author-email: delvidio.neto@outlook.com.br
License: MIT License
Keywords: datas date year month day bussiness day dia util
License-File: LICENSE
Requires-Dist: holidays
